fed3bandit/__init__.py
fed3bandit/fed3bandit/fed3bandit.py
fed3bandit/fed3bandit/fed3bandit_app.py
fed3bandit/fed3bandit/launch_app.py
fed3bandit/fed3bandit/sample_data.CSV
fed3bandit-0.0.5.dist-info/LICENSE
fed3bandit-0.0.5.dist-info/METADATA
fed3bandit-0.0.5.dist-info/WHEEL
fed3bandit-0.0.5.dist-info/top_level.txt
fed3bandit-0.0.5.dist-info/RECORD
