Metadata-Version: 2.1
Name: fed3bandit
Version: 0.0.5
Summary: Package to analyze FED3Bandit files.
Author-email: Alex Legaria <leg.alex96@gmail.com>
License: GNU GENERAL PUBLIC LICENSE
Project-URL: Home, https://github.com/AlexLM96/fed3bandit
Keywords: neuroscience,behavior,research
Classifier: License :: OSI Approved :: GNU General Public License v3 (GPLv3)
Classifier: Development Status :: 3 - Alpha
Classifier: Intended Audience :: Science/Research
Classifier: Programming Language :: Python :: 3
Requires-Python: >=3.6
License-File: LICENSE
Requires-Dist: pandas
Requires-Dist: numpy
Requires-Dist: statsmodels
Requires-Dist: dash
Requires-Dist: dash-bootstrap-components
Requires-Dist: matplotlib
